{"nodes": [{"id": "app_gemini_page_tsx", "label": "page.tsx", "file_type": "code", "source_file": "app/gemini/page.tsx", "source_location": "L1"}, {"id": "page_savekey", "label": "saveKey()", "file_type": "code", "source_file": "app/gemini/page.tsx", "source_location": "L24"}], "edges": [{"source": "app_gemini_page_tsx", "target": "react", "relation": "imports_from", "confidence": "EXTRACTED", "source_file": "app/gemini/page.tsx", "source_location": "L3", "weight": 1.0}, {"source": "app_gemini_page_tsx", "target": "link", "relation": "imports_from", "confidence": "EXTRACTED", "source_file": "app/gemini/page.tsx", "source_location": "L4", "weight": 1.0}, {"source": "app_gemini_page_tsx", "target": "page_savekey", "relation": "contains", "confidence": "EXTRACTED", "source_file": "app/gemini/page.tsx", "source_location": "L24", "weight": 1.0}], "raw_calls": [{"caller_nid": "page_savekey", "callee": "trim", "source_file": "app/gemini/page.tsx", "source_location": "L25"}, {"caller_nid": "page_savekey", "callee": "setItem", "source_file": "app/gemini/page.tsx", "source_location": "L27"}, {"caller_nid": "page_savekey", "callee": "setSavedKey", "source_file": "app/gemini/page.tsx", "source_location": "L28"}, {"caller_nid": "page_savekey", "callee": "setApiKey", "source_file": "app/gemini/page.tsx", "source_location": "L29"}, {"caller_nid": "page_savekey", "callee": "setShowKeyEdit", "source_file": "app/gemini/page.tsx", "source_location": "L30"}]}