{"nodes": [{"id": "lib_cc_fleet_throughput_ts", "label": "throughput.ts", "file_type": "code", "source_file": "lib/cc-fleet/throughput.ts", "source_location": "L1"}, {"id": "throughput_fleetcapacityperday", "label": "fleetCapacityPerDay()", "file_type": "code", "source_file": "lib/cc-fleet/throughput.ts", "source_location": "L81"}, {"id": "throughput_estimateeffortgap", "label": "estimateEffortGap()", "file_type": "code", "source_file": "lib/cc-fleet/throughput.ts", "source_location": "L93"}, {"id": "throughput_revenuefromadditionalaccounts", "label": "revenueFromAdditionalAccounts()", "file_type": "code", "source_file": "lib/cc-fleet/throughput.ts", "source_location": "L126"}], "edges": [{"source": "lib_cc_fleet_throughput_ts", "target": "lib_cc_fleet_types", "relation": "imports_from", "confidence": "EXTRACTED", "source_file": "lib/cc-fleet/throughput.ts", "source_location": "L5", "weight": 1.0}, {"source": "lib_cc_fleet_throughput_ts", "target": "throughput_fleetcapacityperday", "relation": "contains", "confidence": "EXTRACTED", "source_file": "lib/cc-fleet/throughput.ts", "source_location": "L81", "weight": 1.0}, {"source": "lib_cc_fleet_throughput_ts", "target": "throughput_estimateeffortgap", "relation": "contains", "confidence": "EXTRACTED", "source_file": "lib/cc-fleet/throughput.ts", "source_location": "L93", "weight": 1.0}, {"source": "lib_cc_fleet_throughput_ts", "target": "throughput_revenuefromadditionalaccounts", "relation": "contains", "confidence": "EXTRACTED", "source_file": "lib/cc-fleet/throughput.ts", "source_location": "L126", "weight": 1.0}], "raw_calls": [{"caller_nid": "throughput_fleetcapacityperday", "callee": "reduce", "source_file": "lib/cc-fleet/throughput.ts", "source_location": "L85"}, {"caller_nid": "throughput_fleetcapacityperday", "callee": "filter", "source_file": "lib/cc-fleet/throughput.ts", "source_location": "L85"}, {"caller_nid": "throughput_estimateeffortgap", "callee": "now", "source_file": "lib/cc-fleet/throughput.ts", "source_location": "L107"}, {"caller_nid": "throughput_estimateeffortgap", "callee": "getTime", "source_file": "lib/cc-fleet/throughput.ts", "source_location": "L108"}, {"caller_nid": "throughput_estimateeffortgap", "callee": "max", "source_file": "lib/cc-fleet/throughput.ts", "source_location": "L109"}, {"caller_nid": "throughput_estimateeffortgap", "callee": "ceil", "source_file": "lib/cc-fleet/throughput.ts", "source_location": "L109"}, {"caller_nid": "throughput_estimateeffortgap", "callee": "ceil", "source_file": "lib/cc-fleet/throughput.ts", "source_location": "L113"}, {"caller_nid": "throughput_estimateeffortgap", "callee": "round", "source_file": "lib/cc-fleet/throughput.ts", "source_location": "L117"}, {"caller_nid": "throughput_estimateeffortgap", "callee": "round", "source_file": "lib/cc-fleet/throughput.ts", "source_location": "L118"}, {"caller_nid": "throughput_revenuefromadditionalaccounts", "callee": "round", "source_file": "lib/cc-fleet/throughput.ts", "source_location": "L144"}, {"caller_nid": "throughput_revenuefromadditionalaccounts", "callee": "round", "source_file": "lib/cc-fleet/throughput.ts", "source_location": "L145"}, {"caller_nid": "throughput_revenuefromadditionalaccounts", "callee": "round", "source_file": "lib/cc-fleet/throughput.ts", "source_location": "L146"}, {"caller_nid": "throughput_revenuefromadditionalaccounts", "callee": "Number", "source_file": "lib/cc-fleet/throughput.ts", "source_location": "L147"}, {"caller_nid": "throughput_revenuefromadditionalaccounts", "callee": "toFixed", "source_file": "lib/cc-fleet/throughput.ts", "source_location": "L147"}]}